{"cameraMode":{"drawMode":0,"name":"Shaded","section":"Shading Mode"},"sceneLighting":true,"audioPlay":false,"sceneViewState":{"m_AlwaysRefresh":false,"showFog":true,"showSkybox":true,"showFlares":true,"showImageEffects":true,"showParticleSystems":true,"showVisualEffectGraphs":true,"m_FxEnabled":true},"in2DMode":false,"pivot":{"x":-33.17474365234375,"y":-16.131256103515626,"z":-20.179336547851564},"rotation":{"x":0.14460822939872743,"y":-0.7291117906570435,"z":0.16218313574790955,"w":0.6491749882698059},"size":21.465885162353517,"orthographic":false}